orbiter_parsers/__init__.py
orbiter_parsers/file_types/__init__.py
orbiter_parsers/file_types/jil.py
orbiter_parsers/file_types/python.py
orbiter_parsers/file_types/wld.py
orbiter_parsers/parsers/__init__.py
orbiter_parsers/parsers/esp/__init__.py
orbiter_parsers/parsers/esp/grammar/__init__.py
orbiter_parsers/parsers/esp/grammar/esp.cfgr
orbiter_parsers/parsers/jil/__init__.py
orbiter_parsers/parsers/jil/condition_types.py
orbiter_parsers/parsers/jil/conditions.py
orbiter_parsers/parsers/jil/grammar/__init__.py
orbiter_parsers/parsers/jil/grammar/conditions.cfgr
orbiter_parsers/parsers/jil/grammar/jil.cfgr
orbiter_parsers-0.2.6.dist-info/METADATA
orbiter_parsers-0.2.6.dist-info/WHEEL
orbiter_parsers-0.2.6.dist-info/top_level.txt
orbiter_parsers-0.2.6.dist-info/RECORD
