Metadata-Version: 2.4
Name: orbiter-parsers
Version: 0.2.6
Summary: Parsers and FileTypes for various origin export formats that Astronomer's Orbiter tool may encounter.
Author-email: Fritz Davenport <fritz@astronomer.io>, Astronomer <humans@astronomer.io>
Project-URL: Homepage, https://astronomer.io
Project-URL: Source, https://github.com/astronomer/orbiter-parsers
Requires-Python: >=3.10
Requires-Dist: astronomer-orbiter
Requires-Dist: lark
Requires-Dist: jilutil
Requires-Dist: ast2json
Requires-Dist: typing_extensions
Provides-Extra: dev
Requires-Dist: build; extra == "dev"
Requires-Dist: twine>=4.0.2; extra == "dev"
Requires-Dist: pytest>=8.3.5; extra == "dev"
Requires-Dist: pytest-xdist>=3.8.0; extra == "dev"
Requires-Dist: pytest-cov>=4.1; extra == "dev"
Requires-Dist: pytest-sugar>=1.0.0; extra == "dev"
Requires-Dist: black>=23.12.0; extra == "dev"
Requires-Dist: ruff>=0.1.0; extra == "dev"
Requires-Dist: pylint>=3.0.0; extra == "dev"
Requires-Dist: isort>=5.13.0; extra == "dev"
Requires-Dist: pre-commit>=3.6.0; python_version >= "3.9" and extra == "dev"
Requires-Dist: detect-secrets>=1.4.0; extra == "dev"
